{
  "title": "Biological Concept: Plant",
  "concepts": [
    {
      "id": "bio_kingdom_plant",
      "name": "Plant",
      "kr_name": "식물",
      "description": "A living organism of the kind exemplified by trees, shrubs, herbs, grasses, ferns, and mosses, typically growing in a permanent site, absorbing water and inorganic substances through its roots, and synthesizing nutrients in its leaves by photosynthesis using the green pigment chlorophyll.",
      "type": "biological_kingdom",
      "properties": {
        "has_chlorophyll": true,
        "is_autotroph": true
      }
    }
  ]
}
