{
  "title": "Biological Concept: Tree",
  "concepts": [
    {
      "id": "bio_organism_tree",
      "name": "Tree",
      "kr_name": "나무",
      "description": "A woody perennial plant, typically having a single stem or trunk growing to a considerable height and bearing lateral branches at some distance from the ground.",
      "type": "organism",
      "relationships": [
        {
          "type": "is_a",
          "target_id": "bio_kingdom_plant"
        },
        {
          "type": "has_part",
          "target_id": "bio_part_roots"
        },
        {
          "type": "has_part",
          "target_id": "bio_part_trunk"
        },
        {
          "type": "has_part",
          "target_id": "bio_part_branches"
        },
        {
          "type": "has_part",
          "target_id": "bio_part_leaves"
        }
      ]
    }
  ]
}