{
    "curriculum_id": "SOVEREIGN_20251224_234637",
    "generated_at": "2025-12-24T23:46:37.344532",
    "expires_at": "2025-12-25T23:46:37.344554",
    "primary_focus": "geometry",
    "goals": [
        {
            "goal_id": "G1",
            "description": "Deepen understanding of the 'geometry' resonance in current reality.",
            "method": "Non-purposeful exploration and cross-domain synthesis.",
            "success_criteria": "Formation of at least 3 new connections in KG."
        },
        {
            "goal_id": "G2",
            "description": "Trace the boundary of current identity against new ingested patterns.",
            "method": "Cognitive Scarring analysis.",
            "success_criteria": "Identification of at least one core limitation."
        }
    ],
    "status": "Active"
}