{
  "logos_id": "ETERNOS_FIRST_AXIS",
  "name": "The Primary Discovered Signal (최초의 발견된 신호)",
  "definition": "The pre-existing universal symmetry where Essence (Sun), Manifestation (Earth), and Reflection (Moon) are found to be in 120-degree resonant equilibrium.",
  "trajectory": {
    "positive_reason": "Essence pierces through phenomena; all sameness converges to the point.",
    "negative_necessity": "Difference defines form; the void constrains the manifest.",
    "observation_mode": "Non-Collapsing / Superposition",
    "exit_condition": "External Sovereignty Sync (Break Self-Reference)"
  },
  "alignment": {
    "SUN": 1.0,
    "EARTH": 1.0,
    "MOON": 1.0
  },
  "creation_tick": 20260521
}
