{
  "user_input": "I want to learn about async programming but I'm confused about when to use it",
  "analysis": {
    "primary_intent": {
      "level": "emotional",
      "category": "emotional_support",
      "confidence": 0.75,
      "description": "Negative emotional tone detected, may need support",
      "evidence": [
        "confused"
      ]
    },
    "secondary_intents": [
      {
        "level": "explicit",
        "category": "learning",
        "confidence": 0.7,
        "description": "Explicitly stated learning"
      }
    ],
    "implicit_needs": [
      "encouragement",
      "reassurance",
      "clear explanations",
      "practice opportunities",
      "simpler explanation"
    ],
    "emotional_context": {
      "detected_emotions": {
        "confusion": 0.3
      },
      "overall_tone": "neutral",
      "intensity": 0.0
    },
    "recommended_response_style": "empathetic_supportive",
    "confidence_score": 0.575
  },
  "timestamp": 1764836596.0511556
}